[
    {
      "bet_link": "Link",
      "league": "NHL",
      "market": "h2h",
      "odds": 100,
      "page_content": "The odds of the away team Anaheim Ducks defeating the home team Buffalo Sabres on Wednesday, March 15, 2024 at 2024-03-13T14:10:00Z are 100.",
      "sportsbook_name": "BetOnline.ag",
      "team": "Anaheim Ducks",
      "sport": "hockey"
    },
    {
      "bet_link": "Link",
      "league": "NHL",
      "market": "h2h",
      "odds": 110,
      "page_content": "The odds of the away team Arizona Coyotes defeating the home team Carolina Hurricanes on Wednesday, March 15, 2024 at 2024-03-13T14:10:00Z are 110.",
      "sportsbook_name": "BetMGM",
      "team": "Arizona Coyotes",
      "sport": "hockey"
    },
    {
      "bet_link": "Link",
      "league": "NHL",
      "market": "h2h",
      "odds": 120,
      "page_content": "The odds of the away team Boston Bruins defeating the home team Chicago Blackhawks on Wednesday, March 15, 2024 at 2024-03-13T14:10:00Z are 120.",
      "sportsbook_name": "BetRivers",
      "team": "Boston Bruins",
      "sport": "hockey"
    },
    {
      "bet_link": "Link",
      "league": "NHL",
      "market": "h2h",
      "odds": 130,
      "page_content": "The odds of the away team Buffalo Sabres defeating the home team Colorado Avalanche on Wednesday, March 15, 2024 at 2024-03-13T14:10:00Z are 130.",
      "sportsbook_name": "BetUS",
      "team": "Buffalo Sabres",
      "sport": "hockey"
    },
    {
      "bet_link": "Link",
      "league": "NHL",
      "market": "h2h",
      "odds": 140,
      "page_content": "The odds of the away team Calgary Flames defeating the home team Columbus Blue Jackets on Wednesday, March 15, 2024 at 2024-03-13T14:10:00Z are 140.",
      "sportsbook_name": "Bovada",
      "team": "Calgary Flames",
      "sport": "hockey"
    },
    {
      "bet_link": "Link",
      "league": "NHL",
      "market": "h2h",
      "odds": 150,
      "page_content": "The odds of the away team Carolina Hurricanes defeating the home team Dallas Stars on Wednesday, March 15, 2024 at 2024-03-13T14:10:00Z are 150.",
      "sportsbook_name": "DraftKings",
      "team": "Carolina Hurricanes",
      "sport": "hockey"
    },
    {
      "bet_link": "Link",
      "league": "NHL",
      "market": "h2h",
      "odds": 160,
      "page_content": "The odds of the away team Chicago Blackhawks defeating the home team Detroit Red Wings on Wednesday, March 15, 2024 at 2024-03-13T14:10:00Z are 160.",
      "sportsbook_name": "FanDuel",
      "team": "Chicago Blackhawks",
      "sport": "hockey"
    },
    {
      "bet_link": "Link",
      "league": "NHL",
      "market": "h2h",
      "odds": 170,
      "page_content": "The odds of the away team Colorado Avalanche defeating the home team Edmonton Oilers on Wednesday, March 15, 2024 at 2024-03-13T14:10:00Z are 170.",
      "sportsbook_name": "LowVig.ag",
      "team": "Colorado Avalanche",
      "sport": "hockey"
    },
    {
      "bet_link": "Link",
      "league": "NHL",
      "market": "h2h",
      "odds": 180,
      "page_content": "The odds of the away team Columbus Blue Jackets defeating the home team Florida Panthers on Wednesday, March 15, 2024 at 2024-03-13T14:10:00Z are 180.",
      "sportsbook_name": "MyBookie.ag",
      "team": "Columbus Blue Jackets",
      "sport": "hockey"
    },
    {
      "bet_link": "Link",
      "league": "NHL",
      "market": "h2h",
      "odds": 190,
      "page_content": "The odds of the away team Dallas Stars defeating the home team Los Angeles Kings on Wednesday, March 15, 2024 at 2024-03-13T14:10:00Z are 190.",
      "sportsbook_name": "PointsBet (US)",
      "team": "Dallas Stars",
      "sport": "hockey"
    },
    {
      "bet_link": "Link",
      "league": "NHL",
      "market": "h2h",
      "odds": 200,
      "page_content": "The odds of the away team Detroit Red Wings defeating the home team Minnesota Wild on Wednesday, March 15, 2024 at 2024-03-13T14:10:00Z are 200.",
      "sportsbook_name": "SuperBook",
      "team": "Detroit Red Wings",
      "sport": "hockey"
    },
    {
      "bet_link": "Link",
      "league": "NHL",
      "market": "h2h",
      "odds": 210,
      "page_content": "The odds of the away team Edmonton Oilers defeating the home team Nashville Predators on Wednesday, March 15, 2024 at 2024-03-13T14:10:00Z are 210.",
      "sportsbook_name": "Unibet",
      "team": "Edmonton Oilers",
      "sport": "hockey"
    },
    {
      "bet_link": "Link",
      "league": "NHL",
      "market": "h2h",
      "odds": 220,
      "page_content": "The odds of the away team Florida Panthers defeating the home team New Jersey Devils on Wednesday, March 15, 2024 at 2024-03-13T14:10:00Z are 220.",
      "sportsbook_name": "Caesars",
      "team": "Florida Panthers",
      "sport": "hockey"
    },
    {
      "bet_link": "Link",
      "league": "NHL",
      "market": "h2h",
      "odds": 230,
      "page_content": "The odds of the away team Los Angeles Kings defeating the home team New York Islanders on Wednesday, March 15, 2024 at 2024-03-13T14:10:00Z are 230.",
      "sportsbook_name": "WynnBET",
      "team": "Los Angeles Kings",
      "sport": "hockey"
    },
    {
      "bet_link": "Link",
      "league": "NHL",
      "market": "h2h",
      "odds": 240,
      "page_content": "The odds of the away team Minnesota Wild defeating the home team New York Rangers on Wednesday, March 15, 2024 at 2024-03-13T14:10:00Z are 240.",
      "sportsbook_name": "BetPARX",
      "team": "Minnesota Wild",
      "sport": "hockey"
    },
    {
      "bet_link": "Link",
      "league": "NHL",
      "market": "h2h",
      "odds": 250,
      "page_content": "The odds of the away team Montreal Canadiens defeating the home team Ottawa Senators on Wednesday, March 15, 2024 at 2024-03-13T14:10:00Z are 250.",
      "sportsbook_name": "ESPN BET",
      "team": "Montreal Canadiens",
      "sport": "hockey"
    },
    {
      "bet_link": "Link",
      "league": "NHL",
      "market": "h2h",
      "odds": 260,
      "page_content": "The odds of the away team Nashville Predators defeating the home team Philadelphia Flyers on Wednesday, March 15, 2024 at 2024-03-13T14:10:00Z are 260.",
      "sportsbook_name": "DraftKings",
      "team": "Nashville Predators",
      "sport": "hockey"
    },
    {
      "bet_link": "Link",
      "league": "NHL",
      "market": "h2h",
      "odds": 270,
      "page_content": "The odds of the away team New Jersey Devils defeating the home team Pittsburgh Penguins on Wednesday, March 15, 2024 at 2024-03-13T14:10:00Z are 270.",
      "sportsbook_name": "Fliff",
      "team": "New Jersey Devils",
      "sport": "hockey"
    },
    {
      "bet_link": "Link",
      "league": "NHL",
      "market": "h2h",
      "odds": 280,
      "page_content": "The odds of the away team New York Islanders defeating the home team San Jose Sharks on Wednesday, March 15, 2024 at 2024-03-13T14:10:00Z are 280.",
      "sportsbook_name": "Hard Rock Bet",
      "team": "New York Islanders",
      "sport": "hockey"
    },
    {
      "bet_link": "Link",
      "league": "NHL",
      "market": "h2h",
      "odds": 290,
      "page_content": "The odds of the away team New York Rangers defeating the home team Seattle Kraken on Wednesday, March 15, 2024 at 2024-03-13T14:10:00Z are 290.",
      "sportsbook_name": "SI Sportsbook",
      "team": "New York Rangers",
      "sport": "hockey"
    },
    {
      "bet_link": "Link",
      "league": "NHL",
      "market": "h2h",
      "odds": 300,
      "page_content": "The odds of the away team Ottawa Senators defeating the home team St. Louis Blues on Wednesday, March 15, 2024 at 2024-03-13T14:10:00Z are 300.",
      "sportsbook_name": "Tipico",
      "team": "Ottawa Senators",
      "sport": "hockey"
    },
    {
      "bet_link": "Link",
      "league": "NHL",
      "market": "h2h",
      "odds": 310,
      "page_content": "The odds of the away team Philadelphia Flyers defeating the home team Tampa Bay Lightning on Wednesday, March 15, 2024 at 2024-03-13T14:10:00Z are 310.",
      "sportsbook_name": "Betfred PA",
      "team": "Philadelphia Flyers",
      "sport": "hockey"
    },
    {
      "bet_link": "Link",
      "league": "NHL",
      "market": "h2h",
      "odds": 320,
      "page_content": "The odds of the away team Pittsburgh Penguins defeating the home team Toronto Maple Leafs on Wednesday, March 15, 2024 at 2024-03-13T14:10:00Z are 320.",
      "sportsbook_name": "BetMGM",
      "team": "Pittsburgh Penguins",
      "sport": "hockey"
    },
    {
      "bet_link": "Link",
      "league": "NHL",
      "market": "h2h",
      "odds": 330,
      "page_content": "The odds of the away team San Jose Sharks defeating the home team Vancouver Canucks on Wednesday, March 15, 2024 at 2024-03-13T14:10:00Z are 330.",
      "sportsbook_name": "FanDuel",
      "team": "San Jose Sharks",
      "sport": "hockey"
    },
    {
      "bet_link": "Link",
      "league": "NHL",
      "market": "h2h",
      "odds": 340,
      "page_content": "The odds of the away team Seattle Kraken defeating the home team Washington Capitals on Wednesday, March 15, 2024 at 2024-03-13T14:10:00Z are 340.",
      "sportsbook_name": "DraftKings",
      "team": "Seattle Kraken",
      "sport": "hockey"
    },
    {
      "bet_link": "Link",
      "league": "NHL",
      "market": "h2h",
      "odds": 350,
      "page_content": "The odds of the away team St. Louis Blues defeating the home team Winnipeg Jets on Wednesday, March 15, 2024 at 2024-03-13T14:10:00Z are 350.",
      "sportsbook_name": "PointsBet (US)",
      "team": "St. Louis Blues",
      "sport": "hockey"
    },
    {
      "bet_link": "Link",
      "league": "NHL",
      "market": "h2h",
      "odds": 360,
      "page_content": "The odds of the away team Tampa Bay Lightning defeating the home team Anaheim Ducks on Wednesday, March 15, 2024 at 2024-03-13T14:10:00Z are 360.",
      "sportsbook_name": "Unibet",
      "team": "Tampa Bay Lightning",
      "sport": "hockey"
    },
    {
      "bet_link": "Link",
      "league": "NHL",
      "market": "h2h",
      "odds": 370,
      "page_content": "The odds of the away team Toronto Maple Leafs defeating the home team Arizona Coyotes on Wednesday, March 15, 2024 at 2024-03-13T14:10:00Z are 370.",
      "sportsbook_name": "MyBookie.ag",
      "team": "Toronto Maple Leafs",
      "sport": "hockey"
    },
    {
      "bet_link": "Link",
      "league": "NHL",
      "market": "h2h",
      "odds": 380,
      "page_content": "The odds of the away team Vancouver Canucks defeating the home team Boston Bruins on Wednesday, March 15, 2024 at 2024-03-13T14:10:00Z are 380.",
      "sportsbook_name": "Bovada",
      "team": "Vancouver Canucks",
      "sport": "hockey"
    },
    {
      "bet_link": "Link",
      "league": "NHL",
      "market": "h2h",
      "odds": 390,
      "page_content": "The odds of the away team Vegas Golden Knights defeating the home team Calgary Flames on Wednesday, March 15, 2024 at 2024-03-13T14:10:00Z are 390.",
      "sportsbook_name": "BetRivers",
      "team": "Vegas Golden Knights",
      "sport": "hockey"
    },
    {
        "bet_link": "Link",
        "league": "NHL",
        "market": "h2h",
        "odds": 400,
        "page_content": "The odds of the away team Washington Capitals defeating the home team Winnipeg Jets on Wednesday, March 15, 2024 at 2024-03-13T14:10:00Z are 400.",
        "sportsbook_name": "Betfred PA",
        "team": "Washington Capitals",
        "sport": "hockey"
    },
    {
      "bet_link": "Link",
      "league": "NHL",
      "market": "h2h",
      "odds": 400,
      "page_content": "The odds of the away team Winnipeg Jets defeating the home team Carolina Hurricanes on Wednesday, March 15, 2024 at 2024-03-13T14:10:00Z are 400.",
      "sportsbook_name": "WynnBET",
      "team": "Winnipeg Jets",
      "sport": "hockey"
    }
  ]
  